{
  "courses": [
    {
      "id": 1,
      "preview": true,
      "image": "/images/Home/homeCarousel/graphics.jpeg",
      "duration": "30 Classes",
      "status": "Available",
      "title": "Graphics Design",
      "description": "Master the art of graphic design with comprehensive lessons covering design principles, software proficiency, and practical applications.",
      "author": {
        "name": "Cathie Corl",
        "image": "/images/Home/homeCarousel/graphicsAuthor.jpg"
      },
      "category": "design"
    },
    {
      "id": 2,
      "preview": true,
      "image": "/images/Home/homeCarousel/web.jpeg",
      "duration": "43 Classes",
      "status": "Available",
      "title": "Web Design & Development",
      "description": "Explore the fundamentals of web design and development, from HTML/CSS basics to responsive layouts and backend technologies, led by industry experts.",
      "author": {
        "name": "Jobayer Hossain",
        "image": "/images/Home/homeCarousel/webAuthor.jpg"
      },
      "category": "development"
    },
    {
      "id": 3,
      "preview": true,
      "image": "/images/Home/homeCarousel/brand.jpeg",
      "duration": "8hr 12min",
      "status": "Available",
      "title": "Brand & Identity Design",
      "description": "Lorem ipsum dolor sit amet consectetur adipisicing elit. Quia esse eveniet numquam asperiores, ad beatae officia aliquid distinctio culpa possimus?",
      "author": {
        "name": "Jobayer Hossain",
        "image": "/images/Home/homeCarousel/brandAuthor.jpg"
      },
      "category": "design"
    },
    {
      "id": 4,
      "preview": true,
      "image": "/images/Home/homeCarousel/logo.jpeg",
      "duration": "8hr 12min",
      "status": "Available",
      "title": "Advanced Logo Designn",
      "description": "Lorem ipsum dolor sit amet consectetur adipisicing elit. Quia esse eveniet numquam asperiores, ad beatae officia aliquid distinctio culpa possimus?",
      "author": {
        "name": "Jobayer Hossain",
        "image": "/images/Home/homeCarousel/logoAuthor.jpg"
      },
      "category": "design"
    },
    {
      "id": 5,
      "preview": true,
      "image": "/images/Home/homeCarousel/marketing.jpg",
      "duration": "8hr 12min",
      "status": "Available",
      "title": "Marketing Analytics 101",
      "description": "Lorem ipsum dolor sit amet consectetur adipisicing elit. Quia esse eveniet numquam asperiores, ad beatae officia aliquid distinctio culpa possimus?",
      "author": {
        "name": "Jobayer Hossain",
        "image": "/images/Home/homeCarousel/marketingAuthor.jpg"
      },
      "category": "marketing"
    },
    {
      "id": 6,
      "preview": true,
      "image": "/images/Home/homeCarousel/mobile.jpeg",
      "duration": "8hr 12min",
      "status": "Available",
      "title": "Mobile App Development",
      "description": "Lorem ipsum dolor sit amet consectetur adipisicing elit. Quia esse eveniet numquam asperiores, ad beatae officia aliquid distinctio culpa possimus?",
      "author": {
        "name": "Jobayer Hossain",
        "image": "/images/Home/homeCarousel/mobileAuthor.jpg"
      },
      "category": "development"
    }
  ],
  "categories": [
    {
      "id": 1,
      "category": "design",
      "image": "../images/Home/category/design.svg",
      "title": "Design",
      "description": "Lorem ipsum dolor sit amet consectetur adipisicing elit. Quia esse eveniet numquam asperiores.",
      "video": "12 Courses"
    },
    {
      "id": 2,
      "image": "../images/Home/category/development.svg",
      "title": "Development",
      "description": "Lorem ipsum dolor sit amet consectetur adipisicing elit. Quia esse eveniet numquam asperiores.",
      "video": "5 Courses"
    },
    {
      "id": 3,
      "image": "../images/Home/category/marketing.svg",
      "title": "Graphics design 101",
      "description": "Lorem ipsum dolor sit amet consectetur adipisicing elit. Quia esse eveniet numquam asperiores.",
      "video": "7 Courses"
    }
  ],
  "review": [
    {
      "id": "1",
      "image": "/images/Home/review/author1.jpg",
      "say": "Duis aute irure dolor in reprehenderit in voluptate velit esse cillum dolore eu fugiat nulla pariatur. Excepteur sint",
      "name": "Sophie Moore",
      "position": "UX Designer at Agency",
      "ratings": 4.5
    },
    {
      "id": "2",
      "image": "/images/Home/review/author1.jpg",
      "say": "Duis aute irure dolor in reprehenderit in voluptate velit esse cillum dolore eu fugiat nulla pariatur. Excepteur sint",
      "name": "Sophie Moore",
      "position": "UX Designer at Agency",
      "ratings": 5
    },
    {
      "id": "3",
      "image": "/images/Home/review/author1.jpg",
      "say": "Duis aute irure dolor in reprehenderit in voluptate velit esse cillum dolore eu fugiat nulla pariatur. Excepteur sint",
      "name": "Sophie Moore",
      "position": "UX Designer at Agency",
      "ratings": 4.7
    },
    {
      "id": "4",
      "image": "/images/Home/review/author1.jpg",
      "say": "Duis aute irure dolor in reprehenderit in voluptate velit esse cillum dolore eu fugiat nulla pariatur. Excepteur sint",
      "name": "Sophie Moore",
      "position": "UX Designer at Agency",
      "ratings": 5
    },
    {
      "id": "5",
      "image": "/images/Home/review/author1.jpg",
      "say": "Duis aute irure dolor in reprehenderit in voluptate velit esse cillum dolore eu fugiat nulla pariatur. Excepteur sint",
      "name": "Sophie Moore",
      "position": "UX Designer at Agency",
      "ratings": 5
    }
  ],
  "category": [
    {
      "id": 1,
      "image": "../images/Home/category/design.svg",
      "title": "Design",
      "description": "Master the art of design with courses covering graphic design, UI/UX, and more, equipping you with creative skills and industry knowledge.",
      "video": "12 Courses"
    },
    {
      "id": 2,
      "image": "../images/Home/category/development.svg",
      "title": "Development",
      "description": "Explore the world of development with courses in web development, software engineering, and more, empowering you to build innovative solutions.",
      "video": "5 Courses"
    },
    {
      "id": 3,
      "image": "../images/Home/category/marketing.svg",
      "title": "Computer Basic",
      "description": "Delve into the world of marketing with courses covering digital marketing strategies, social media, SEO, and more, enabling you to reach target audiences effectively.",
      "video": "7 Courses"
    }
  ],
  "featuredCourse":{
    "courseTitle":"Digital Marketing",
    "courseDescription" : "Explore the dynamic world of digital marketing strategies, including SEO, social media, and content marketing, to drive successful campaigns and boost online presence.",
    "instructorImage" : "/images/courses/blank-author-image.webp",
    "instructorName" : "Khondoker Sakibul Habib",
    "courseImage" : "/images/courses/digital-marketing.webp",
    "courseDuration" : "30 Classes",
    "courseStatus" : "Available"
  }
}
